nextcore/__init__.py
nextcore/common/__init__.py
nextcore/common/dispatcher.py
nextcore/common/errors.py
nextcore/common/json.py
nextcore/common/maybe_coro.py
nextcore/common/times_per/__init__.py
nextcore/common/times_per/priority_queue_container.py
nextcore/common/times_per/times_per.py
nextcore/common/undefined.py
nextcore/gateway/__init__.py
nextcore/gateway/close_code.py
nextcore/gateway/decompressor.py
nextcore/gateway/errors.py
nextcore/gateway/exponential_backoff.py
nextcore/gateway/op_code.py
nextcore/gateway/shard.py
nextcore/gateway/shard_manager.py
nextcore/http/__init__.py
nextcore/http/authentication/__init__.py
nextcore/http/authentication/base.py
nextcore/http/authentication/bearer.py
nextcore/http/authentication/bot.py
nextcore/http/bucket.py
nextcore/http/bucket_metadata.py
nextcore/http/client/__init__.py
nextcore/http/client/base_client.py
nextcore/http/client/client.py
nextcore/http/errors.py
nextcore/http/global_rate_limiter/__init__.py
nextcore/http/global_rate_limiter/base.py
nextcore/http/global_rate_limiter/limited.py
nextcore/http/global_rate_limiter/unlimited.py
nextcore/http/rate_limit_storage.py
nextcore/http/request_session.py
nextcore/http/route.py
nextcore/py.typed
nextcore-2.0.2.dist-info/LICENSE
nextcore-2.0.2.dist-info/METADATA
nextcore-2.0.2.dist-info/WHEEL
nextcore-2.0.2.dist-info/RECORD
