Metadata-Version: 2.1
Name: nextcore
Version: 2.0.2
Summary: A low level Discord API wrapper
Home-page: https://github.com/nextsnake/nextcore
License: MIT
Keywords: discord,bot,wrapper,api
Author: tag-epic
Requires-Python: >=3.8,<4.0
Classifier: Development Status :: 3 - Alpha
Classifier: Framework :: AsyncIO
Classifier: Framework :: aiohttp
Classifier: Intended Audience :: Developers
Classifier: License :: OSI Approved :: MIT License
Classifier: Natural Language :: English
Classifier: Operating System :: OS Independent
Classifier: Programming Language :: Cython
Classifier: Programming Language :: Python :: 3
Classifier: Programming Language :: Python :: 3.8
Classifier: Programming Language :: Python :: 3.9
Classifier: Programming Language :: Python :: 3.10
Classifier: Programming Language :: Python :: 3.11
Classifier: Programming Language :: Python :: 3.12
Classifier: Programming Language :: Python :: Implementation :: CPython
Classifier: Topic :: Communications :: Chat
Classifier: Topic :: Software Development :: Libraries :: Python Modules
Classifier: Typing :: Typed
Provides-Extra: speed
Requires-Dist: aiohttp (>=3.6.0,<4.0.0)
Requires-Dist: discord-typings (>=0.5.0,<0.6.0)
Requires-Dist: frozendict (>=2.3.0,<3.0.0)
Requires-Dist: orjson (>=3.6.8,<4.0.0) ; extra == "speed"
Requires-Dist: types-frozendict (>=2.0.6,<3.0.0)
Requires-Dist: types-orjson (>=3.6.2,<4.0.0) ; extra == "speed"
Requires-Dist: typing-extensions (>=4.1.1,<5.0.0)
Project-URL: Bug Tracker, https://github.com/nextsnake/nextcore/issues
Project-URL: Documentation, https://nextcore.readthedocs.io
Project-URL: Discord, https://discord.gg/3RFUm3eP5c
Project-URL: Repository, https://github.com/nextsnake/nextcore
